external_resources_io/__init__.py
external_resources_io/cli.py
external_resources_io/config.py
external_resources_io/exit_status.py
external_resources_io/input.py
external_resources_io/log.py
external_resources_io/py.typed
external_resources_io/terraform/__init__.py
external_resources_io/terraform/generators.py
external_resources_io/terraform/plan.py
external_resources_io/terraform/run.py
external_resources_io-0.6.2.dist-info/METADATA
external_resources_io-0.6.2.dist-info/WHEEL
external_resources_io-0.6.2.dist-info/entry_points.txt
external_resources_io-0.6.2.dist-info/RECORD
