Metadata-Version: 2.4
Name: external-resources-io
Version: 0.6.2
Summary: Util classes for AppSRE External Resources system
Project-URL: homepage, https://github.com/app-sre/external-resources-io
Project-URL: repository, https://github.com/app-sre/external-resources-io
Project-URL: documentation, https://github.com/app-sre/external-resources-io
Author-email: Jordi Piriz <jpiriz@redhat.com>
License: Apache 2.0
Requires-Python: >=3.11
Requires-Dist: pydantic-settings>=2.7.1
Requires-Dist: pydantic>=2.10.0
Provides-Extra: cli
Requires-Dist: typer>=0.15.1; extra == 'cli'
